optidash/__init__.py
optidash/client.py
optidash-1.0.2.dist-info/LICENSE
optidash-1.0.2.dist-info/METADATA
optidash-1.0.2.dist-info/WHEEL
optidash-1.0.2.dist-info/top_level.txt
optidash-1.0.2.dist-info/RECORD
