Metadata-Version: 2.1
Name: optidash
Version: 1.0.2
Summary: Official Python integration for Optidash API
Home-page: https://github.com/optidash-ai/optidash-python
Download-URL: https://github.com/optidash-ai/optidash-python/archive/1.0.2.tar.gz
Author: Optidash GmbH
Author-email: support@optidash.ai
License: MIT
Keywords: optidash image optimization processing resizing resizer cropping scaling masking watermarking filtering thumbnails pic picture photo face face detection visual watermark filter crop mask resize resizer thumbs thumbnail thumbnails jpg jpeg png gif svg bmp psd tiff heic
Classifier: Development Status :: 5 - Production/Stable
Classifier: Intended Audience :: Developers
Classifier: Natural Language :: English
Classifier: License :: OSI Approved :: MIT License
Classifier: Programming Language :: Python :: 3.6
Classifier: Programming Language :: Python :: 3.7
Classifier: Programming Language :: Python :: 3.8
Classifier: Programming Language :: Python :: 3.9
Classifier: Programming Language :: Python :: 3.10
Classifier: Topic :: Software Development
Classifier: Topic :: Software Development :: Libraries
Classifier: Topic :: Software Development :: Libraries :: Python Modules
Classifier: Topic :: Utilities
License-File: LICENSE
Requires-Dist: requests
